LICENSE
README.md
setup.py
phonlp/__init__.py
phonlp/annotate_model.py
phonlp/run_script.py
phonlp.egg-info/PKG-INFO
phonlp.egg-info/SOURCES.txt
phonlp.egg-info/dependency_links.txt
phonlp.egg-info/requires.txt
phonlp.egg-info/top_level.txt
phonlp/models/__init__.py
phonlp/models/run_phonlp.py
phonlp/models/common/__init__.py
phonlp/models/common/biaffine.py
phonlp/models/common/chuliu_edmonds.py
phonlp/models/common/crf.py
phonlp/models/common/data.py
phonlp/models/common/doc.py
phonlp/models/common/dropout.py
phonlp/models/common/loss.py
phonlp/models/common/seq2seq_constant.py
phonlp/models/common/seq2seq_utils.py
phonlp/models/common/trainer.py
phonlp/models/common/utils.py
phonlp/models/common/vocab.py
phonlp/models/depparse/__init__.py
phonlp/models/depparse/scorer.py
phonlp/models/jointmodel/__init__.py
phonlp/models/jointmodel/data.py
phonlp/models/jointmodel/model.py
phonlp/models/jointmodel/trainer.py
phonlp/models/ner/__init__.py
phonlp/models/ner/scorer.py
phonlp/models/ner/utils.py
phonlp/models/ner/vocab.py
phonlp/models/pos/__init__.py
phonlp/models/pos/scorer.py
phonlp/models/pos/vocab.py
phonlp/utils/__init__.py
phonlp/utils/conll.py
phonlp/utils/conll18_ud_eval.py