Metadata-Version: 2.1
Name: phonlp
Version: 0.3.5
Summary: PhoNLP: A joint multi-task learning model for Vietnamese part-of-speech tagging, named entity recognition and dependency parsing
Home-page: https://github.com/VinAIResearch/PhoNLP
Author: Linh The Nguyen and Dat Quoc Nguyen
Author-email: v.linhnt140@vinai.io
Maintainer: linhnt
Maintainer-email: v.linhnt140@vinai.io
Classifier: Development Status :: 4 - Beta
Classifier: Intended Audience :: Developers
Classifier: License :: OSI Approved :: MIT License
Classifier: Programming Language :: Python :: 3.7
Requires-Python: >=3.6
License-File: LICENSE
